{
  "ALV.DE": {
    "price": 373.899994,
    "time": 1755781320000
  },
  "BAS.DE": {
    "price": 47.400002,
    "time": 1755781320000
  },
  "CYR.DE": {
    "price": 2.54,
    "time": 1755775020000
  },
  "MBG.DE": {
    "price": 53.970001,
    "time": 1755781320000
  },
  "RHM.DE": {
    "price": 1603.5,
    "time": 1755781260000
  },
  "S188.DE": {
    "price": 8.2,
    "time": 1755775020000
  },
  "S92.DE": {
    "price": 22.620001,
    "time": 1755780960000
  },
  "SAP.DE": {
    "price": 231.949997,
    "time": 1755781320000
  },
  "SIE.DE": {
    "price": 233.0,
    "time": 1755781320000
  }
}